{
  "schemaVersion": "0.1",
  "ticker": "HYPD",
  "secCik": "0001682639",
  "asOf": "2025-12-04",
  "generatedAt": "2026-03-09T13:43:06.563Z",
  "listing": {
    "country": "US",
    "exchangeMic": "XNAS",
    "currency": "USD"
  },
  "holdings": {
    "asset": "HYPE",
    "amount": 1862195,
    "source": {
      "holdingsSource": "press-release",
      "holdingsSourceUrl": "https://ir.hyperiondefi.com/news-events/press-releases/detail/300/hyperion-defi-announces-receipt-of-kinetiq-airdrop-partnership-with-native-markets-and-purchase-of-150000-additional-hype",
      "holdingsAccession": null
    }
  },
  "shares": {
    "sharesForMnav": 24400000,
    "sharesOutstandingFD": null,
    "asOf": "2025-11-10",
    "source": {
      "sharesSource": "SEC 10-Q Nov 14, 2025 (8.1M common + 16.3M from preferred conversion)",
      "sharesSourceUrl": "/filings/hypd/0001104659-25-111671"
    }
  },
  "balanceSheet": {
    "cashReserves": 8223180,
    "restrictedCash": null,
    "totalDebt": 7656005,
    "preferredEquity": 544,
    "asOf": "2025-09-30",
    "source": {
      "cashSourceUrl": "/filings/hypd/0001104659-25-111671",
      "debtSourceUrl": "/filings/hypd/0001104659-25-111671",
      "preferredSourceUrl": "/filings/hypd/0001104659-25-111671"
    }
  },
  "verification": {
    "status": "pending"
  }
}
